Basics/Flipflops/SR_Flipflop/SR_Flipflop.srcs/sources_1/new/srff.v
`timescale 1ns / 1ps
//////////////////////////////////////////////////////////////////////////////////
// Company: 
// Engineer: 
// 
// Create Date: 11.08.2025 23:41:24
// Design Name: 
// Module Name: srff
// Project Name: 
// Target Devices: 
// Tool Versions: 
// Description: 
// 
// Dependencies: 
// 
// Revision:
// Revision 0.01 - File Created
// Additional Comments:
// 
//////////////////////////////////////////////////////////////////////////////////


module srff(sr,clk,q,qb);
input[1:0]sr,clk;
output q,qb;
reg q,qb;

always @(posedge clk)begin
case(sr)
2'b00:q=q;
2'b01:q=0;
2'b10:q=1;
2'b11:q=1'bz;
endcase
end 
always @(*)begin
 qb=~q;
end
endmodule

Basics/Flipflops/SR_Flipflop/SR_Flipflop.srcs/sim_1/new/srff_tb.v
`timescale 1ns / 1ps
//////////////////////////////////////////////////////////////////////////////////
// Company: 
// Engineer: 
// 
// Create Date: 11.08.2025 23:48:52
// Design Name: 
// Module Name: srff_tb
// Project Name: 
// Target Devices: 
// Tool Versions: 
// Description: 
// 
// Dependencies: 
// 
// Revision:
// Revision 0.01 - File Created
// Additional Comments:
// 
//////////////////////////////////////////////////////////////////////////////////


module srff_tb();
reg [1:0]sr,clk;
wire q,qb;

srff dut(.sr(sr),.clk(clk),.q(q),.qb(qb));

initial begin
clk=0;
forever 
#2 clk=~clk;
end 
initial begin
$dumpfile("dump.vcd");
$dumpvars(1);
end
initial begin
sr=2'b00;
#5
sr=2'b01; 
#5
sr=2'b10; 
#5
sr=2'b11; 
#5
sr=2'b10; 
#5
sr=2'b01; 
#5
$finish();
end 
endmodule

Basics/Flipflops/SR_Flipflop/SR_Flipflop.sim/sim_1/behav/xsim/dump.vcd
$date
   Mon Aug 11 23:54:38 2025
$end

$version
  2025.1.0
  $dumpfile ("dump.vcd") 
$end

$timescale
  1ps
$end

$scope module srff_tb $end
$var reg 2 ! sr [1:0] $end
$var reg 2 " clk [1:0] $end
$var wire 1 # q $end
$var wire 1 $ qb $end
$upscope $end
$scope module glbl $end
$upscope $end
$enddefinitions $end

#0
$dumpvars
b0 !
b0 "
x#
x$
$end

#2000
b11 "

#4000
b0 "

#5000
b1 !

#6000
b11 "
0#
1$

#8000
b0 "

#10000
b10 !
b11 "
1#
0$

#12000
b0 "

#14000
b11 "

#15000
b11 !

#16000
b0 "

#18000
b11 "
z#
x$

#20000
b10 !
b0 "

#22000
b11 "
1#
0$

#24000
b0 "

#25000
b1 !

#26000
b11 "
0#
1$

#28000
b0 "
